Metadata-Version: 2.1
Name: Auto-Mouse-Mover
Version: 0.1.0
Summary: Move your mouse and keep that Teams icon green!
Author: Ryan Rickgauer
Author-email: rrickgauer1@gmail.com
Project-URL: Documentation, https://github.com/rrickgauer/Mouse-Mover
Project-URL: Source Code, https://github.com/rrickgauer/Mouse-Mover
Project-URL: Issue Tracker, https://github.com/rrickgauer/Mouse-Mover/issues
